{
  "generatedAt": "2026-07-12T11:38:28.092Z",
  "scope": "odds-api-live-runtime-phase-audit",
  "pass": true,
  "baseUrl": "http://127.0.0.1:3002",
  "event": {
    "providerEventId": "f9aa13a662d1658e5a02cfc06d6a2d73",
    "sportKey": "soccer_fifa_world_cup",
    "title": "Spain vs. France",
    "commenceTime": "2026-07-14T19:00:00Z",
    "localSlug": "odds-api-single-soccer-test"
  },
  "selectedMarket": {
    "id": "78ea76f1-fc8f-419b-ac21-2554d79093f6",
    "slug": "odds-api-single-soccer-test-totals-7439c2d603",
    "title": "Spain vs. France: Total Goals 2.5",
    "marketType": "total_goals",
    "marketGroupKey": "totals",
    "line": "2.5",
    "outcomeId": "dd0797bc-e297-4c19-b55c-ccf1bb96dace",
    "outcomeName": "Over +2.5",
    "referenceTokenId": "odds-api-88263b2c42d6b2f5c6dbbda4"
  },
  "health": {
    "ok": true,
    "status": 200,
    "body": {
      "status": "ok",
      "db": "connected",
      "env": "development",
      "timestamp": "2026-07-12T11:38:28.034Z"
    },
    "error": null
  },
  "quote": {
    "ok": true,
    "status": 200,
    "body": {
      "marketId": "78ea76f1-fc8f-419b-ac21-2554d79093f6",
      "quotes": [
        {
          "outcomeId": "dd0797bc-e297-4c19-b55c-ccf1bb96dace",
          "outcomeName": "Over +2.5",
          "bestBid": "0.47",
          "bestAsk": "0.55",
          "bestBidSize": 200,
          "bestAskSize": 200,
          "midPrice": "0.51",
          "lastPrice": "0.47",
          "lastTradeAt": "2026-07-12T07:16:40.841Z"
        },
        {
          "outcomeId": "ee7237f3-ee58-4a66-a092-adaa58b3547f",
          "outcomeName": "Under +2.5",
          "bestBid": null,
          "bestAsk": null,
          "bestBidSize": null,
          "bestAskSize": null,
          "midPrice": null,
          "lastPrice": null,
          "lastTradeAt": null
        }
      ]
    },
    "error": null
  },
  "artifactAgesHours": {
    "liveProof": 4.54,
    "onboarding": 0.9,
    "readiness": 0.9,
    "runtimeStatus": 0.44,
    "runtimeLaunch": 0.45,
    "supervisor": 0.45,
    "supervisorProcess": 0.27,
    "internalTesterRuntime": 0.27,
    "localRuntimeTask": 0.02,
    "continuousSupervisor": 0.44,
    "staleGuardProof": 2.13,
    "staleGuardRun": 2.01,
    "lifecycleControls": 0.9,
    "lifecycleScheduler": 0.9,
    "lifecycleSchedulerRun": 0.45,
    "settlementReadiness": 0.9,
    "settlementExecution": 0.61,
    "resultSettlementExecution": 0.15,
    "manualSettlement": 0.9,
    "resultIngestion": 0.45,
    "resultSettlement": 0.45,
    "resultSettlementRun": 0.45,
    "makerSeed": 0.45,
    "s23Visible": 4.36
  },
  "requirements": [
    {
      "id": "survey-existing-runtime-services",
      "priority": "P0",
      "requirement": "Existing backend/provider/bot/runtime services are surveyed and classified.",
      "status": "complete",
      "evidence": [
        "docs/mobile/BACKEND_LIVE_RUNTIME_SURVEY.md",
        "docs/mobile/MARKET_MAKER_LIVE_RUNTIME_REPORT.md"
      ],
      "notes": null
    },
    {
      "id": "provider-live-refresh",
      "priority": "P0",
      "requirement": "One upcoming soccer event can refresh from live provider odds with quota protection.",
      "status": "complete",
      "evidence": [
        "docs/mobile/harness/odds-api-live-runtime/one-event-live-runtime-summary.redacted.json"
      ],
      "notes": "quotaUsed=13, quotaRemaining=459, eventStart=2026-07-14T19:00:00Z"
    },
    {
      "id": "refresh-mode-truth",
      "priority": "P0",
      "requirement": "Runtime distinguishes live provider refresh from replay/cached checks.",
      "status": "complete",
      "evidence": [
        "docs/mobile/harness/odds-api-live-runtime/one-event-runtime-status-summary.redacted.json",
        "docs/mobile/harness/odds-api-live-runtime/one-event-onboarding-summary.redacted.json"
      ],
      "notes": null
    },
    {
      "id": "quota-policy",
      "priority": "P0",
      "requirement": "Provider quota is protected and API key is environment-only.",
      "status": "complete",
      "evidence": [
        "docs/mobile/harness/odds-api-live-runtime/one-event-live-runtime-summary.redacted.json",
        "docs/mobile/harness/odds-api-live-runtime/one-event-onboarding-summary.redacted.json",
        "docs/mobile/ODDS_PROVIDER_REFRESH_POLICY.md"
      ],
      "notes": null
    },
    {
      "id": "market-maker-liquidity",
      "priority": "P0",
      "requirement": "Market maker liquidity is available and shifted worse than provider.",
      "status": "complete",
      "evidence": [
        "docs/mobile/harness/odds-api-live-runtime/shifted-maker-seed-summary.redacted.json",
        "http://127.0.0.1:3002/api/markets/78ea76f1-fc8f-419b-ac21-2554d79093f6/quote"
      ],
      "notes": null
    },
    {
      "id": "market-maker-continuity",
      "priority": "P0",
      "requirement": "Market maker continuity is explicitly known.",
      "status": "complete",
      "evidence": [
        "docs/mobile/harness/odds-api-live-runtime/one-event-live-supervisor-summary.redacted.json",
        "docs/mobile/harness/odds-api-live-runtime/one-event-live-supervisor-process-summary.redacted.json",
        "docs/mobile/harness/odds-api-live-runtime/one-event-continuous-supervisor-proof-summary.redacted.json"
      ],
      "notes": "Known truth: maker reseeds and lifecycle checks run across repeated local supervisor cycles without provider quota. It is not an installed unattended service."
    },
    {
      "id": "supervisor-result-ingestion",
      "priority": "P0",
      "requirement": "Supervisor loop runs provider-shaped result ingestion before trusted-result settlement dry-run checks.",
      "status": "complete",
      "evidence": [
        "docs/mobile/harness/odds-api-live-runtime/one-event-live-supervisor-summary.redacted.json",
        "docs/mobile/harness/odds-api-live-runtime/one-event-continuous-supervisor-proof-summary.redacted.json",
        "docs/mobile/harness/odds-api-live-runtime/one-event-result-ingestion-summary.redacted.json",
        "docs/mobile/harness/odds-api-live-runtime/one-event-result-settlement-run-summary.redacted.json"
      ],
      "notes": "Replay-mode result ingestion is proven inside repeated supervisor cycles. Opt-in live score ingestion is available through quota-capped supervisor controls; installed unattended polling and settlement execution remain P1."
    },
    {
      "id": "mobile-trading-flow",
      "priority": "P0",
      "requirement": "Mobile can trade the one upcoming event end-to-end and Portfolio/history reflect it.",
      "status": "complete",
      "evidence": [
        "docs/mobile/harness/odds-api-live-runtime/one-event-live-runtime-summary.redacted.json",
        "docs/mobile/harness/odds-api-live-runtime/one-event-live-readiness-summary.redacted.json",
        "docs/mobile/harness/cycle-LIVEODDSS23-odds-api-live-runtime-s23/cycle-LIVEODDSS23-odds-api-s23-visible-flow.json"
      ],
      "notes": null
    },
    {
      "id": "stale-handling",
      "priority": "P0",
      "requirement": "Stale odds handling is proven and available in supervisor workflow.",
      "status": "complete",
      "evidence": [
        "docs/mobile/harness/odds-api-live-runtime/one-event-stale-guard-summary.redacted.json",
        "docs/mobile/harness/odds-api-live-runtime/one-event-stale-guard-run-summary.redacted.json",
        "docs/mobile/harness/odds-api-live-runtime/one-event-live-supervisor-summary.redacted.json"
      ],
      "notes": null
    },
    {
      "id": "event-open-suspend-close",
      "priority": "P0",
      "requirement": "Event lifecycle open, suspended, and closed behavior is proven.",
      "status": "complete",
      "evidence": [
        "docs/mobile/harness/odds-api-live-runtime/event-lifecycle-controls-summary.redacted.json",
        "docs/mobile/harness/odds-api-live-runtime/event-lifecycle-scheduler-summary.redacted.json",
        "docs/mobile/harness/odds-api-live-runtime/one-event-lifecycle-scheduler-run-summary.redacted.json"
      ],
      "notes": null
    },
    {
      "id": "settlement-readiness",
      "priority": "P0",
      "requirement": "Settlement readiness, trusted result mapping, guarded settlement, and local scheduler run are documented/proven.",
      "status": "complete",
      "evidence": [
        "docs/mobile/harness/odds-api-live-runtime/one-event-settlement-readiness-summary.redacted.json",
        "docs/mobile/harness/odds-api-live-runtime/one-event-manual-settlement-summary.redacted.json",
        "docs/mobile/harness/odds-api-live-runtime/one-event-result-ingestion-summary.redacted.json",
        "docs/mobile/harness/odds-api-live-runtime/one-event-result-settlement-summary.redacted.json",
        "docs/mobile/harness/odds-api-live-runtime/one-event-result-settlement-run-summary.redacted.json",
        "docs/mobile/EVENT_LIFECYCLE_RUNBOOK.md"
      ],
      "notes": "Provider-shaped score ingestion can produce trusted result JSON in replay mode, and the local scheduler can dry-run that result. Live score ingestion is explicit and quota-guarded through the command or supervisor controls; installed unattended official result polling remains P1."
    },
    {
      "id": "settlement-execution-disposable",
      "priority": "P0",
      "requirement": "Settlement execution is proven on a disposable local market without mutating the active tester event.",
      "status": "complete",
      "evidence": [
        "docs/mobile/harness/odds-api-live-runtime/one-event-settlement-execution-summary.redacted.json"
      ],
      "notes": "Execution proof uses a fresh disposable local market. Active one-event tester settlement still requires trusted operator confirmation."
    },
    {
      "id": "trusted-result-scheduler-execution-disposable",
      "priority": "P0",
      "requirement": "Trusted-result settlement scheduler execution is proven on a disposable sportsbook-shaped event without mutating the active tester event.",
      "status": "complete",
      "evidence": [
        "docs/mobile/harness/odds-api-live-runtime/one-event-result-settlement-scheduler-execution-summary.redacted.json"
      ],
      "notes": "This proves the scheduler execute path with reviewed trusted result JSON and an exact confirmation phrase. It still does not install unattended official-result polling."
    },
    {
      "id": "backend-runtime-health",
      "priority": "P0",
      "requirement": "Backend health and selected quote route are reachable locally.",
      "status": "complete",
      "evidence": [
        "http://127.0.0.1:3002/api/health",
        "http://127.0.0.1:3002/api/markets/78ea76f1-fc8f-419b-ac21-2554d79093f6/quote"
      ],
      "notes": null
    },
    {
      "id": "internal-tester-runtime-manager",
      "priority": "P0",
      "requirement": "Local internal tester runtime manager can report backend, Expo, Postgres, S23, and supervisor status without spending provider quota.",
      "status": "complete",
      "evidence": [
        "docs/mobile/harness/odds-api-live-runtime/internal-tester-runtime-manager-summary.redacted.json"
      ],
      "notes": "This proves local operator visibility/control for internal testing. It reuses external backend/Expo listeners when present and only stops manager-owned backend/Expo processes."
    },
    {
      "id": "unattended-service",
      "priority": "P1",
      "requirement": "Install unattended provider/maker/lifecycle services.",
      "status": "open",
      "evidence": [
        "docs/mobile/harness/odds-api-live-runtime/one-event-live-supervisor-summary.redacted.json",
        "docs/mobile/harness/odds-api-live-runtime/one-event-live-supervisor-process-summary.redacted.json",
        "docs/mobile/harness/odds-api-live-runtime/internal-tester-runtime-manager-summary.redacted.json",
        "docs/mobile/harness/odds-api-live-runtime/local-runtime-task-summary.redacted.json",
        "docs/mobile/harness/odds-api-live-runtime/one-event-continuous-supervisor-proof-summary.redacted.json"
      ],
      "notes": "Repeated local supervisor cycles, process-tree stop support, an internal tester runtime manager, and a dry-run Windows scheduled-task install plan are proven. No OS/service manager install has been applied."
    },
    {
      "id": "official-result-auto-settlement",
      "priority": "P1",
      "requirement": "Automatically ingest official soccer results and settle markets.",
      "status": "open",
      "evidence": [
        "docs/mobile/harness/odds-api-live-runtime/one-event-settlement-readiness-summary.redacted.json",
        "docs/mobile/harness/odds-api-live-runtime/one-event-settlement-execution-summary.redacted.json",
        "docs/mobile/harness/odds-api-live-runtime/one-event-result-settlement-scheduler-execution-summary.redacted.json",
        "docs/mobile/harness/odds-api-live-runtime/one-event-manual-settlement-summary.redacted.json",
        "docs/mobile/harness/odds-api-live-runtime/one-event-result-ingestion-summary.redacted.json",
        "docs/mobile/harness/odds-api-live-runtime/one-event-result-settlement-summary.redacted.json",
        "docs/mobile/harness/odds-api-live-runtime/one-event-result-settlement-run-summary.redacted.json"
      ],
      "notes": "Provider-shaped result ingestion replay and trusted-result scheduler execution are proven on disposable local evidence. Live score ingestion is available only behind explicit live flags plus THE_ODDS_API_KEY, including the quota-capped supervisor path. Installed unattended provider result polling and unconfirmed active-event execution remain future work."
    }
  ],
  "conclusion": {
    "p0Complete": true,
    "openP0": [],
    "openP1": [
      "unattended-service",
      "official-result-auto-settlement"
    ],
    "phaseCompleteForLocalInternalRuntime": true,
    "fullProductionRuntimeComplete": false,
    "runtimeTruth": "Local one-event runtime is internally usable with cached/live-proofed provider data, fake-token trading, local internal tester runtime status/control, supervisor monitoring, provider-shaped replay result ingestion, opt-in quota-capped live result ingestion controls, and trusted-result settlement dry-run scheduling. It is not a production unattended daemon and does not install unattended official result polling."
  }
}
