{
  "generatedAt": "2026-07-15T05:54:23.423Z",
  "scope": "odds-api-one-event-cached-live-restore",
  "pass": true,
  "sourceSummaryPath": "docs/mobile/harness/odds-api-live-runtime/one-event-live-runtime-summary.redacted.json",
  "event": {
    "id": "bdd748d4-8784-459d-a612-a54903892c89",
    "slug": "odds-api-single-soccer-test",
    "title": "Argentina vs. England",
    "startTime": "2026-07-15T19:00:00.000Z",
    "source": "the-odds-api",
    "externalEventId": "ced22494ae0bbb8cc4f7108bf6f493df"
  },
  "markets": {
    "restoredMarketCount": 19,
    "restoredOutcomeCount": 40,
    "staleReplayClosedCount": 3,
    "visibleMarketCount": 19,
    "sportsbookMarketCount": 3,
    "contractFixtureMarketCount": 16,
    "visibleTitles": [
      "Argentina vs. England: Team to advance",
      "Argentina vs. England: England in regulation",
      "Argentina vs. England: Argentina in regulation",
      "Argentina vs. England: Draw in regulation",
      "Argentina vs. England: Regulation Time Winner",
      "Argentina vs. England: Regulation Time Winner",
      "Argentina vs. England: England -3.5",
      "Argentina vs. England: England -2.5",
      "Argentina vs. England: England -1.5",
      "Argentina vs. England: England +1.5",
      "Argentina vs. England: England +2.5",
      "Argentina vs. England: England +3.5",
      "Argentina vs. England: Total Goals 2.5",
      "Argentina vs. England: Total goals 0.5",
      "Argentina vs. England: Total goals 1.5",
      "Argentina vs. England: Total goals 2.5",
      "Argentina vs. England: Total goals 3.5",
      "Argentina vs. England: Total goals 4.5",
      "Argentina vs. England: Total goals 5.5"
    ]
  },
  "checks": {
    "eventTitleRestored": true,
    "eventUpcomingOrCurrent": true,
    "restoredMarketsVisible": true,
    "restoredTradableOutcomes": true,
    "staleReplayMarketsClosed": true
  },
  "gaps": {
    "p0": [],
    "p1": [
      "This is a quota-free cached restore; fresh live provider refresh still requires THE_ODDS_API_KEY explicitly."
    ],
    "p2": [
      "Per-provider-event slugs should replace the reusable local test slug before multi-event onboarding."
    ]
  }
}
