{
  "pass": true,
  "generatedAt": "2026-07-14T05:24:36.794Z",
  "startedAt": "2026-07-14T05:24:36.589Z",
  "scope": "odds-api-one-event-shifted-maker-seed",
  "mode": "seed-resting-shifted-maker-quotes",
  "event": {
    "id": "3722a197-6584-41e8-ab71-bfede8eedbf0",
    "slug": "odds-api-single-soccer-test",
    "title": "Spain vs. France",
    "startTime": "2026-07-14T19:00:00.000Z"
  },
  "selectedMarket": {
    "id": "78ea76f1-fc8f-419b-ac21-2554d79093f6",
    "slug": "odds-api-single-soccer-test-totals-7439c2d603",
    "title": "Spain vs. France: Total Goals 2.5",
    "marketType": "total_goals",
    "marketGroupKey": "totals",
    "line": "2.5",
    "outcomeId": "30fbc915-74ca-4809-a0c4-cd54c3236aa4",
    "outcomeName": "Over +2.5",
    "referenceTokenId": "odds-api-88263b2c42d6b2f5c6dbbda4"
  },
  "providerSnapshot": {
    "fetchedAt": "2026-07-14T04:49:08.576Z",
    "ageMs": 2128065,
    "maxSnapshotAgeMs": 86400000,
    "allowStale": false,
    "source": "sportsbook-odds",
    "referenceBid": 0.4839,
    "referenceAsk": 0.5239,
    "outcomePrice": 0.5039
  },
  "maker": {
    "id": "5fc93227-c4c6-4b0a-934c-9f7749cf8b96",
    "username": "odds_live_runtime_shifted_maker_45826e25"
  },
  "collateralRepair": {
    "repaired": false,
    "before": "150",
    "after": "150",
    "byOutcome": [
      {
        "outcomeId": "30fbc915-74ca-4809-a0c4-cd54c3236aa4",
        "code": "over-2-5",
        "shares": "150"
      },
      {
        "outcomeId": "fe72ef40-ee22-4cc8-9830-bb46a4bf6c15",
        "code": "under-2-5",
        "shares": "150"
      }
    ]
  },
  "plan": {
    "quoteOffsetTicks": 2,
    "plannedBid": 0.46,
    "plannedAsk": 0.59,
    "adjustments": [
      "plannedAsk moved above existing best bid 0.58"
    ],
    "preSeedBook": {
      "bestBid": 0.58,
      "bestAsk": null,
      "openOrderCount": 1,
      "orders": [
        {
          "side": "BUY",
          "price": "0.58",
          "remaining": "36.9",
          "username": "mobile_route_fill_maker_70dca32b"
        }
      ]
    },
    "size": "200",
    "mintQuantity": "200"
  },
  "canceledPreviousOrders": [],
  "restingOrders": [
    {
      "id": "dda7c641-8e1c-4570-8769-46a27ca9557a",
      "username": "odds_live_runtime_shifted_maker_45826e25",
      "side": "BUY",
      "price": "0.46",
      "remaining": "200",
      "status": "OPEN"
    },
    {
      "id": "fcc11b6f-5812-487b-9e76-33eeb92217c1",
      "username": "odds_live_runtime_shifted_maker_45826e25",
      "side": "SELL",
      "price": "0.59",
      "remaining": "200",
      "status": "OPEN"
    }
  ],
  "quoteRoute": {
    "url": "http://127.0.0.1:3002/api/markets/78ea76f1-fc8f-419b-ac21-2554d79093f6/quote",
    "ok": true,
    "status": 200,
    "selectedOutcomeQuote": {
      "outcomeId": "30fbc915-74ca-4809-a0c4-cd54c3236aa4",
      "outcomeName": "Over +2.5",
      "bestBid": "0.58",
      "bestAsk": "0.59",
      "bestBidSize": 36.9,
      "bestAskSize": 200,
      "midPrice": "0.585",
      "lastPrice": "0.58",
      "lastTradeAt": "2026-07-14T05:22:27.634Z"
    }
  },
  "checks": {
    "eventLoaded": true,
    "marketLive": true,
    "snapshotFresh": true,
    "shiftedBidWorseThanProvider": true,
    "shiftedAskWorseThanProvider": true,
    "makerBidResting": true,
    "makerAskResting": true,
    "quoteRouteShowsBid": true,
    "quoteRouteShowsAsk": true
  },
  "gaps": {
    "p0": [],
    "p1": [
      "this command seeds resting shifted maker quotes once; it is reusable but not an unattended daemon by itself",
      "provider refresh still comes from the bounded live proof or future daemon"
    ],
    "p2": [
      "multi-market inventory-aware quoting remains future work"
    ]
  }
}
