{
    "cycle":  "BATCHS23",
    "result":  "pass",
    "generatedAt":  "2026-07-11T07:18:58.2030870Z",
    "device":  "adb-R3CW20LFMLW-7OpoO6._adb-tls-connect._tcp",
    "model":  "SM-S911U1",
    "backendBaseUrl":  "http://127.0.0.1:3002",
    "mobileApiBaseUrl":  "http://172.16.200.14:3002",
    "expoPort":  8289,
    "keyId":  "redacted",
    "apiKey":  "redacted",
    "eventSlug":  "argentina-vs-egypt",
    "lineMarketGroupKey":  "spread",
    "lineMarketType":  "spread",
    "lineValue":  "1.5",
    "lineOutcomeSide":  "away",
    "lineOutcomeLabel":  "Egypt +1.5",
    "lineTapPrefix":  "event-detail-outcome-spread-",
    "seededCounterparty":  true,
    "counterpartyProof":  "docs\\mobile\\harness\\cycle-BATCHS23-current-mvp-proof\\cycle-BATCHS23-current-mvp-counterparty.json",
    "cleanupProof":  null,
    "cashoutBidPrice":  null,
    "cashoutCounterpartyProof":  null,
    "assertions":  {
                       "homeShowsCurrentMatch":  true,
                       "homeShowsProviderWinnerLocalLinesDisclosure":  true,
                       "liveShowsProviderWinnerLocalLinesDisclosure":  true,
                       "detailShowsGameLines":  true,
                       "detailShowsLineFamilyReadiness":  true,
                       "detailShowsProviderUnavailableLineFamilies":  true,
                       "detailShowsProviderWinnerLocalLineSplit":  true,
                       "lineMarketsAreContractFixture":  true,
                       "orderbookHidden":  true,
                       "ticketPreservesLine":  true,
                       "swipeSubmitReachedPortfolio":  true,
                       "portfolioOpenOrderPreservesLineSource":  true,
                       "fixtureLineOrderAccepted":  false,
                       "openOrderVisible":  false,
                       "openOrderSourceBadgeVisible":  false,
                       "filledPositionVisible":  true,
                       "historyShowsEmptyStateUntilFill":  false,
                       "filledHistoryVisible":  true,
                       "cancelSubmitted":  false,
                       "canceledHistoryVisible":  false,
                       "cashoutTicketOpened":  false,
                       "cashoutSellSubmitted":  false,
                       "cashoutHistoryVisible":  false
                   },
    "artifacts":  [
                      "docs\\mobile\\screenshots\\cycle-BATCHS23-current-mvp-proof\\cycle-BATCHS23-current-mvp-home.png",
                      "docs\\mobile\\screenshots\\cycle-BATCHS23-current-mvp-proof\\cycle-BATCHS23-current-mvp-live.png",
                      "docs\\mobile\\screenshots\\cycle-BATCHS23-current-mvp-proof\\cycle-BATCHS23-current-mvp-detail-top.png",
                      "docs\\mobile\\screenshots\\cycle-BATCHS23-current-mvp-proof\\cycle-BATCHS23-current-mvp-lines.png",
                      "docs\\mobile\\screenshots\\cycle-BATCHS23-current-mvp-proof\\cycle-BATCHS23-current-mvp-ticket.png",
                      "docs\\mobile\\screenshots\\cycle-BATCHS23-current-mvp-proof\\cycle-BATCHS23-current-mvp-ticket-ready.png",
                      "docs\\mobile\\screenshots\\cycle-BATCHS23-current-mvp-proof\\cycle-BATCHS23-current-mvp-after-submit.png",
                      "docs\\mobile\\screenshots\\cycle-BATCHS23-current-mvp-proof\\cycle-BATCHS23-current-mvp-portfolio-history.png",
                      "docs\\mobile\\harness\\cycle-BATCHS23-current-mvp-proof\\cycle-BATCHS23-current-mvp-counterparty.json"
                  ]
}
