{
  "cycle": "JS",
  "scope": "cashout-route-sell-safety",
  "generatedAt": "2026-07-13T21:30:17.004Z",
  "marketId": "3e4c6bea-a791-4a93-a6df-7330712cd225",
  "outcomeId": "05ec585a-8f7d-4054-b641-719470b1ebd4",
  "checks": {
    "noPositionSellRejected": true,
    "oversellRejected": true,
    "validFullPositionSellAccepted": true,
    "failedAttemptsStored": true
  },
  "responses": {
    "nakedSell": {
      "error": {
        "code": "INSUFFICIENT_BALANCE",
        "message": "Insufficient shares"
      }
    },
    "oversell": {
      "error": {
        "code": "INSUFFICIENT_BALANCE",
        "message": "Insufficient available shares"
      }
    },
    "validSell": {
      "order": {
        "id": "4ccc07ea-8a90-43de-8bb6-adaad699b765",
        "marketId": "3e4c6bea-a791-4a93-a6df-7330712cd225",
        "outcomeId": "05ec585a-8f7d-4054-b641-719470b1ebd4",
        "side": "SELL",
        "price": "0.45",
        "size": "2",
        "remaining": "2",
        "reservedNotional": "0",
        "status": "OPEN",
        "type": "LIMIT",
        "clientOrderId": null,
        "apiKeyId": null,
        "contractSide": null,
        "selection": null
      },
      "fills": [],
      "balance": {
        "availableUSDC": "98",
        "lockedUSDC": "0"
      },
      "position": {
        "shares": "2",
        "reservedShares": "2",
        "avgCost": "0.5",
        "realizedPnl": "0"
      }
    }
  },
  "apiOrderRequests": [
    {
      "idempotencyKey": "cycle-js-naked-sell-1783978216861-3ozm4d",
      "status": "FAILED",
      "responseStatus": 409,
      "errorCode": "INSUFFICIENT_BALANCE",
      "errorMessage": "Insufficient shares",
      "orderId": null
    },
    {
      "idempotencyKey": "cycle-js-oversell-1783978216861-3ozm4d",
      "status": "FAILED",
      "responseStatus": 409,
      "errorCode": "INSUFFICIENT_BALANCE",
      "errorMessage": "Insufficient available shares",
      "orderId": null
    },
    {
      "idempotencyKey": "cycle-js-valid-sell-1783978216861-3ozm4d",
      "status": "SUCCEEDED",
      "responseStatus": 200,
      "errorCode": null,
      "errorMessage": null,
      "orderId": "4ccc07ea-8a90-43de-8bb6-adaad699b765"
    }
  ],
  "remainingPosition": {
    "shares": "2",
    "reservedShares": "2"
  }
}
